coviddollar.py
coviddollar-0.0.3.dist-info/METADATA
coviddollar-0.0.3.dist-info/WHEEL
coviddollar-0.0.3.dist-info/entry_points.txt
coviddollar-0.0.3.dist-info/top_level.txt
coviddollar-0.0.3.dist-info/RECORD
